{
  "db_name": "PostgreSQL",
  "query": "\n        SELECT \n            id,\n            user_id,\n            side as \"side!: OrderSide\",\n            energy_amount,\n            trigger_price as \"trigger_price!\",\n            trigger_type as \"trigger_type!: TriggerType\",\n            trigger_status as \"trigger_status!: TriggerStatus\",\n            price_per_kwh as limit_price,\n            trailing_offset,\n            expires_at,\n            created_at as \"created_at!\",\n            triggered_at\n        FROM trading_orders\n        WHERE user_id = $1 AND trigger_type IS NOT NULL\n        ORDER BY created_at DESC\n        LIMIT 100\n        ",
  "describe": {
    "columns": [
      {
        "ordinal": 0,
        "name": "id",
        "type_info": "Uuid"
      },
      {
        "ordinal": 1,
        "name": "user_id",
        "type_info": "Uuid"
      },
      {
        "ordinal": 2,
        "name": "side!: OrderSide",
        "type_info": {
          "Custom": {
            "name": "order_side",
            "kind": {
              "Enum": [
                "buy",
                "sell"
              ]
            }
          }
        }
      },
      {
        "ordinal": 3,
        "name": "energy_amount",
        "type_info": "Numeric"
      },
      {
        "ordinal": 4,
        "name": "trigger_price!",
        "type_info": "Numeric"
      },
      {
        "ordinal": 5,
        "name": "trigger_type!: TriggerType",
        "type_info": {
          "Custom": {
            "name": "trigger_type",
            "kind": {
              "Enum": [
                "stop_loss",
                "take_profit",
                "trailing_stop"
              ]
            }
          }
        }
      },
      {
        "ordinal": 6,
        "name": "trigger_status!: TriggerStatus",
        "type_info": {
          "Custom": {
            "name": "trigger_status",
            "kind": {
              "Enum": [
                "pending",
                "triggered",
                "cancelled",
                "expired"
              ]
            }
          }
        }
      },
      {
        "ordinal": 7,
        "name": "limit_price",
        "type_info": "Numeric"
      },
      {
        "ordinal": 8,
        "name": "trailing_offset",
        "type_info": "Numeric"
      },
      {
        "ordinal": 9,
        "name": "expires_at",
        "type_info": "Timestamptz"
      },
      {
        "ordinal": 10,
        "name": "created_at!",
        "type_info": "Timestamptz"
      },
      {
        "ordinal": 11,
        "name": "triggered_at",
        "type_info": "Timestamptz"
      }
    ],
    "parameters": {
      "Left": [
        "Uuid"
      ]
    },
    "nullable": [
      false,
      false,
      true,
      false,
      true,
      true,
      true,
      false,
      true,
      true,
      true,
      true
    ]
  },
  "hash": "644bc1e555ced723e94cce0c00a1e5e3189b75d377bf1872b07636ec6feb695e"
}
